molting/__init__.py
molting/main.py
molting-0.3.1.dist-info/entry_points.txt
molting-0.3.1.dist-info/LICENSE
molting-0.3.1.dist-info/WHEEL
molting-0.3.1.dist-info/METADATA
molting-0.3.1.dist-info/RECORD
