Metadata-Version: 2.1
Name: molting
Version: 0.3.1
Summary: Automatically bump your project files to the latest version.
Home-page: https://github.com/lucasmelin/molting
License: MIT
Author: Lucas Melin
Author-email: lucas.melin@gmail.com
Requires-Python: >=3.8,<4.0
Classifier: Intended Audience :: Developers
Classifier: License :: OSI Approved :: MIT License
Classifier: Programming Language :: Python :: 3
Classifier: Programming Language :: Python :: 3.10
Classifier: Programming Language :: Python :: 3.8
Classifier: Programming Language :: Python :: 3.9
Classifier: Topic :: Software Development
Requires-Dist: loguru (>=0.6.0,<0.7.0)
Project-URL: Bug Tracker, https://github.com/lucasmelin/molting/issues
Project-URL: Repository, https://github.com/lucasmelin/molting
